data_validate/__init__.py
data_validate/config/__init__.py
data_validate/config/config.py
data_validate/controllers/__init__.py
data_validate/controllers/context/__init__.py
data_validate/controllers/context/data_context.py
data_validate/controllers/context/general_context.py
data_validate/controllers/processor.py
data_validate/controllers/report/__init__.py
data_validate/controllers/report/model_report.py
data_validate/controllers/report/report_generator_files.py
data_validate/helpers/__init__.py
data_validate/helpers/base/__init__.py
data_validate/helpers/base/constant_base.py
data_validate/helpers/base/data_args.py
data_validate/helpers/base/file_system_utils.py
data_validate/helpers/base/logger_manager.py
data_validate/helpers/base/metadata_info.py
data_validate/helpers/common/__init__.py
data_validate/helpers/common/formatting/__init__.py
data_validate/helpers/common/formatting/error_formatting.py
data_validate/helpers/common/formatting/number_formatting.py
data_validate/helpers/common/formatting/text_formatting.py
data_validate/helpers/common/generation/__init__.py
data_validate/helpers/common/generation/combinations.py
data_validate/helpers/common/processing/__init__.py
data_validate/helpers/common/processing/collections_processing.py
data_validate/helpers/common/processing/data_cleaning.py
data_validate/helpers/common/validation/__init__.py
data_validate/helpers/common/validation/column_validation.py
data_validate/helpers/common/validation/data_validation.py
data_validate/helpers/common/validation/graph_processing.py
data_validate/helpers/common/validation/legend_processing.py
data_validate/helpers/common/validation/proportionality_data_validation.py
data_validate/helpers/common/validation/tree_data_validation.py
data_validate/helpers/common/validation/value_data_validation.py
data_validate/helpers/tools/__init__.py
data_validate/helpers/tools/data_loader/__init__.py
data_validate/helpers/tools/data_loader/api/__init__.py
canoa_data_validate-0.7.64.dist-info/METADATA
canoa_data_validate-0.7.64.dist-info/WHEEL
canoa_data_validate-0.7.64.dist-info/entry_points.txt
canoa_data_validate-0.7.64.dist-info/licenses/LICENSE
canoa_data_validate-0.7.64.dist-info/RECORD
