Metadata-Version: 2.4
Name: canoa_data_validate
Version: 0.7.64
Summary: O data_validate é um validador e processador de planilhas, que automatiza a checagem de integridade e estrutura de arquivos de dados da plataforma AdaptaBrasil. Ele é especialmente útil para projetos que exigem padronização e validação rigorosa de dados tabulares, como pesquisas científicas, bancos de dados ambientais e sistemas de indicadores.
License-Expression: MIT
License-File: LICENSE
Keywords: data validation,data processing,spreadsheet validation,data integrity,tabular data,scientific research,environmental data,indicator systems
Author: Mário de Araújo Carvalho
Author-email: mariodearaujocarvalho@gmail.com
Requires-Python: >=3.12
Classifier: Programming Language :: Python
Requires-Dist: babel (>=2.17.0,<3.0.0)
Requires-Dist: chardet (>=5.2.0,<6.0.0)
Requires-Dist: jinja2 (>=3.1.6,<4.0.0)
Requires-Dist: networkx (>=3.5,<4.0)
Requires-Dist: pandas (>=2.2.3,<3.0.0)
Requires-Dist: pandas-stubs (>=2.2.3.250527,<3.0.0)
Requires-Dist: pdfkit (>=1.0.0,<2.0.0)
Requires-Dist: pyenchant (>=3.2.2,<4.0.0)
Requires-Dist: python-calamine (>=0.5.4,<0.6.0)
Project-URL: Bug Tracker, https://github.com/AdaptaBrasil/data_validate/issues
Project-URL: Changelog, https://github.com/AdaptaBrasil/data_validate/blob/dev/CHANGELOG.md
Project-URL: Documentation, https://github.com/AdaptaBrasil/data_validate/docs
Project-URL: Homepage, https://github.com/AdaptaBrasil/
Project-URL: Repository, https://github.com/AdaptaBrasil/data_validate.git
